horos_io/__init__.py
horos_io/_config.py
horos_io/_legacy.py
horos_io/_utils.py
horos_io/cli.py
horos_io/cmr.py
horos_io/core.py
horos_io/ui.py
horos_io/validation.py
horos_io-0.1.2.20.dist-info/entry_points.txt
horos_io-0.1.2.20.dist-info/LICENSE
horos_io-0.1.2.20.dist-info/WHEEL
horos_io-0.1.2.20.dist-info/METADATA
horos_io-0.1.2.20.dist-info/RECORD
